kaomi_client/__init__.py
kaomi_client/__main__.py
kaomi_client/functions.py
kaomi_client/globals.py
kaomi_client/kaomi_client.py
kaomi_client-0.7.2.dist-info/METADATA
kaomi_client-0.7.2.dist-info/WHEEL
kaomi_client-0.7.2.dist-info/top_level.txt
kaomi_client-0.7.2.dist-info/RECORD
