Metadata-Version: 2.1
Name: kaomi-client
Version: 0.7.2
Summary: This package contains the client endpoint for the Kaomi deployer. Kaomi client has to be run on the deployer system.
Home-page: https://gitlab.linkspirit.it/linkspirit/kaomi-deployer.git
Author: Linkspirit Team
Author-email: tecnici@linkspirit.it
License: UNKNOWN
Platform: UNKNOWN
Classifier: Programming Language :: Python :: 3
Classifier: Operating System :: OS Independent
Requires-Python: >=3
Requires-Dist: requests
Requires-Dist: requests-toolbelt
Requires-Dist: requests-futures
